vidsnap/__init__.py
vidsnap/__main__.py
vidsnap/utils.py
vidsnap-0.1.0.dist-info/LICENSE
vidsnap-0.1.0.dist-info/METADATA
vidsnap-0.1.0.dist-info/WHEEL
vidsnap-0.1.0.dist-info/entry_points.txt
vidsnap-0.1.0.dist-info/top_level.txt
vidsnap-0.1.0.dist-info/RECORD
