Metadata-Version: 2.1
Name: vidsnap
Version: 0.1.0
Summary: Vidsnap is a fast multithreaded tool to split videos into images.
Home-page: https://github.com/jarviscodes/vidsnap
Author: Jarvis Codes
Author-email: jarvis@jayradz.com
License: MIT
Platform: UNKNOWN
Classifier: Programming Language :: Python :: 3
License-File: LICENSE
Requires-Dist: click
Requires-Dist: colorama
Requires-Dist: opencv-python
